{
  "api": "mtop.damai.wireless.search.search",
  "data": {
    "currentTime": 1575882179676,
    "projectInfo": [
      {
        "discountRate": "7",
        "promotionTags": [],
        "logicLabelInfo": {},
        "siteStatus": 3,
        "latitude": 31.222792,
        "isEticket": false,
        "recReasonType": 2,
        "videos": [],
        "cityId": "872",
        "type": "1",
        "categoryName": "舞蹈芭蕾",
        "priceLow": "80",
        "cityName": "上海",
        "subTitle": "",
        "rankingList": {
          "title": "舞蹈芭蕾榜NO.2",
          "type": 1
        },
        "venueId": 56852,
        "subHead": "",
        "id": 609776959123,
        "isSelectSeat": true,
        "longitude": 121.541252,
        "venueCity": "上海",
        "nearestPerformTime": 1577790900000,
        "isNewItem": 1,
        "followStatus": 0,
        "showTag": "",
        "showTime": "2019.12.31 周二 19:15",
        "isSnapUp": false,
        "showStatus": {
          "id": 0,
          "desc": "去购票"
        },
        "logicAddress": "东方艺术中心-歌剧厅",
        "ipvuv": 3231,
        "isAtmospheric": false,
        "isLocal": 0,
        "venueName": "东方艺术中心-歌剧厅",
        "priceStr": "80-680",
        "upTime": 1575598680000,
        "isGeneralAgent": false,
        "tourProjects": [],
        "recReason": "入选舞蹈芭蕾畅销榜TOP10",
        "name": "古巴西班牙舞蹈团舞剧《剧院魅影》",
        "verticalPic": "https://img.alicdn.com/bao/uploaded/https://img.alicdn.com/imgextra/i3/2251059038/O1CN01g0WHqs2GdSDYRIDSA_!!2251059038.jpg",
        "formattedPriceStr": "80-680"
      },
      {
        "promotionTags": [],
        "logicLabelInfo": {},
        "siteStatus": 3,
        "latitude": 31.229624,
        "isEticket": false,
        "recReasonType": 2,
        "videos": [],
        "cityId": "872",
        "type": "0",
        "categoryName": "舞蹈芭蕾",
        "priceLow": "120",
        "cityName": "上海",
        "subTitle": "朱鹮",
        "rankingList": {
          "title": "上海大剧院NO.1",
          "type": 1
        },
        "venueId": 56,
        "subHead": "《朱鹮》是一部纯美的舞剧，关注环境保护、关注人与自然的和谐相处",
        "id": 180264,
        "isSelectSeat": true,
        "longitude": 121.471805,
        "venueCity": "上海",
        "nearestPerformTime": 1578482100000,
        "isNewItem": 0,
        "followStatus": 0,
        "showTag": "",
        "showTime": "2020.01.08 19:15",
        "isSnapUp": false,
        "showStatus": {
          "id": 0,
          "desc": "去购票"
        },
        "logicAddress": "上海",
        "ipvuv": 3240,
        "isAtmospheric": false,
        "isLocal": 0,
        "venueName": "上海大剧院-大剧场",
        "priceStr": "120-580",
        "upTime": 1575000421000,
        "isGeneralAgent": false,
        "tourProjects": [],
        "name": "舞剧《朱鹮》",
        "verticalPic": "https://pimg.dmcdn.cn/perform/project/1802/180264_n.jpg?_t=1575000555031",
        "formattedPriceStr": "120-580"
      },
      {
        "promotionTags": [],
        "logicLabelInfo": {},
        "siteStatus": 3,
        "latitude": 31.229624,
        "isEticket": false,
        "recReasonType": 2,
        "videos": [],
        "cityId": "872",
        "type": "0",
        "categoryName": "舞蹈芭蕾",
        "priceLow": "180",
        "cityName": "上海",
        "subTitle": "王者之舞",
        "rankingList": {
          "title": "上海大剧院NO.2",
          "type": 1
        },
        "venueId": 56,
        "subHead": "无法抵挡的视听盛宴",
        "id": 180204,
        "isSelectSeat": true,
        "longitude": 121.471805,
        "venueCity": "上海",
        "nearestPerformTime": 1579000500000,
        "isNewItem": 0,
        "followStatus": 0,
        "showTag": "",
        "showTime": "2020.01.14-01.19",
        "isSnapUp": false,
        "showStatus": {
          "id": 0,
          "desc": "去购票"
        },
        "logicAddress": "上海",
        "ipvuv": 6953,
        "isAtmospheric": false,
        "isLocal": 0,
        "venueName": "上海大剧院-大剧场",
        "priceStr": "180-980",
        "upTime": 1574151954000,
        "isGeneralAgent": false,
        "tourProjects": [],
        "name": "迈克尔·弗莱利《王者之舞》",
        "verticalPic": "https://pimg.dmcdn.cn/perform/project/1802/180204_n.jpg?_t=1574152875623",
        "formattedPriceStr": "180-980"
      },
      {
        "discountRate": "8.5",
        "promotionTags": [],
        "logicLabelInfo": {},
        "siteStatus": 3,
        "latitude": 31.199479,
        "isEticket": false,
        "recReasonType": 2,
        "videos": [],
        "cityId": "872",
        "type": "1",
        "categoryName": "舞蹈芭蕾",
        "priceLow": "180",
        "cityName": "上海",
        "subTitle": "",
        "venueId": 61013,
        "subHead": "",
        "id": 605445779645,
        "isSelectSeat": true,
        "longitude": 121.394781,
        "venueCity": "上海",
        "nearestPerformTime": 1578742200000,
        "isNewItem": 1,
        "followStatus": 0,
        "showTag": "",
        "showTime": "2020.01.11-01.12",
        "isSnapUp": false,
        "showStatus": {
          "id": 0,
          "desc": "去购票"
        },
        "logicAddress": "上海",
        "ipvuv": 13496,
        "isAtmospheric": false,
        "isLocal": 0,
        "venueName": "上海国际舞蹈中心-大剧场",
        "priceStr": "180-880",
        "upTime": 1570500229000,
        "isGeneralAgent": false,
        "tourProjects": [],
        "name": "俄罗斯马林斯基明星芭蕾舞团《天鹅湖》2020亚洲巡演上海站",
        "verticalPic": "https://img.alicdn.com/bao/uploaded/i4/2251059038/O1CN01kkaelr2GdSCzqPXRJ_!!0-item_pic.jpg",
        "formattedPriceStr": "180-880"
      },
      {
        "promotionTags": [],
        "logicLabelInfo": {},
        "siteStatus": 3,
        "latitude": 31.199479,
        "isEticket": false,
        "recReasonType": 2,
        "videos": [],
        "cityId": "872",
        "type": "1",
        "categoryName": "舞蹈芭蕾",
        "priceLow": "80",
        "cityName": "上海",
        "subTitle": "",
        "venueId": 61013,
        "subHead": "",
        "id": 607525274003,
        "isSelectSeat": true,
        "longitude": 121.394781,
        "venueCity": "上海",
        "nearestPerformTime": 1576236600000,
        "isNewItem": 1,
        "followStatus": 0,
        "showTag": "",
        "showTime": "2019.12.13 周五 19:30",
        "isSnapUp": false,
        "showStatus": {
          "id": 0,
          "desc": "去购票"
        },
        "logicAddress": "上海",
        "ipvuv": 2666,
        "isAtmospheric": false,
        "isLocal": 0,
        "venueName": "上海国际舞蹈中心-大剧场",
        "priceStr": "80-680",
        "upTime": 1573119824000,
        "isGeneralAgent": true,
        "tourProjects": [],
        "name": "上海芭蕾舞团建团40周年系列演出 经典版芭蕾舞剧《天鹅湖》Ballet Swan Lake （Grand Version）Performed by Shanghai Ballet",
        "verticalPic": "https://img.alicdn.com/bao/uploaded/i3/2251059038/O1CN01WtJUzO2GdSDW7q7Pf_!!0-item_pic.jpg",
        "formattedPriceStr": "80-680"
      },
      {
        "promotionTags": [],
        "logicLabelInfo": {},
        "siteStatus": 3,
        "latitude": 30.941621,
        "isEticket": false,
        "recReasonType": 2,
        "videos": [],
        "cityId": "872",
        "type": "1",
        "categoryName": "舞蹈芭蕾",
        "priceLow": "180",
        "cityName": "上海",
        "subTitle": "",
        "venueId": 2199004,
        "subHead": "",
        "id": 608510016813,
        "isSelectSeat": true,
        "longitude": 121.48446,
        "venueCity": "上海",
        "nearestPerformTime": 1576926900000,
        "isNewItem": 1,
        "followStatus": 0,
        "showTag": "",
        "showTime": "2019.12.21-12.22",
        "isSnapUp": false,
        "showStatus": {
          "id": 0,
          "desc": "去购票"
        },
        "logicAddress": "上海",
        "ipvuv": 736,
        "isAtmospheric": false,
        "isLocal": 0,
        "venueName": "九棵树未来艺术中心-大剧场",
        "priceStr": "180-680",
        "upTime": 1574996418000,
        "isGeneralAgent": false,
        "tourProjects": [],
        "name": "圣彼得堡芭蕾舞剧院《天鹅湖》",
        "verticalPic": "https://img.alicdn.com/bao/uploaded/i4/2251059038/O1CN012JtRNG2GdSDVp9CVz_!!2-item_pic.png",
        "formattedPriceStr": "180-680"
      },
      {
        "promotionTags": [],
        "logicLabelInfo": {},
        "siteStatus": 3,
        "latitude": 31.199479,
        "isEticket": false,
        "recReasonType": 2,
        "videos": [
          {
            "vid": "XNDQwMjY2MTEwOA==",
            "picUrl": "https://vthumb.ykimg.com/054106015DA92074000001759803919F",
            "title": "（宣传片）西班牙国粹 吉普赛人灵魂深处的情感释放 当代弗拉门戈《弗拉门戈的重生》",
            "type": 1
          },
          {
            "picUrl": "https://img.alicdn.com/imgextra/i3/2251059038/O1CN01sdRr6a2GdSCzw4qkh_!!2251059038.jpg",
            "type": 2
          },
          {
            "picUrl": "https://img.alicdn.com/imgextra/i3/2251059038/O1CN01KmUsE42GdSD0f7NHj_!!2251059038.jpg",
            "type": 2
          },
          {
            "picUrl": "https://img.alicdn.com/imgextra/i3/2251059038/O1CN01IylsyQ2GdSCyQZiXP_!!2251059038.jpg",
            "type": 2
          },
          {
            "picUrl": "https://img.alicdn.com/imgextra/i1/2251059038/O1CN01RHyXdR2GdSCv7tDAr_!!2251059038.jpg",
            "type": 2
          }
        ],
        "cityId": "872",
        "type": "1",
        "categoryName": "舞蹈芭蕾",
        "isVideoSupport": true,
        "priceLow": "180",
        "cityName": "上海",
        "subTitle": "",
        "venueId": 61013,
        "subHead": "",
        "id": 605490976082,
        "isSelectSeat": true,
        "longitude": 121.394781,
        "venueCity": "上海",
        "nearestPerformTime": 1576841400000,
        "isNewItem": 1,
        "followStatus": 0,
        "showTag": "",
        "showTime": "2019.12.20-12.22",
        "isSnapUp": false,
        "showStatus": {
          "id": 0,
          "desc": "去购票"
        },
        "logicAddress": "上海",
        "ipvuv": 5859,
        "isAtmospheric": false,
        "isLocal": 0,
        "venueName": "上海国际舞蹈中心-大剧场",
        "priceStr": "180-680",
        "upTime": 1571219211000,
        "isGeneralAgent": false,
        "tourProjects": [],
        "name": "西班牙国粹 吉普赛人灵魂深处的情感释放 当代弗拉门戈《弗拉门戈的重生》",
        "verticalPic": "https://img.alicdn.com/bao/uploaded/https://img.alicdn.com/imgextra/i1/2251059038/O1CN01yby48A2GdSCzvbmPb_!!2251059038.jpg",
        "formattedPriceStr": "180-680"
      },
      {
        "promotionTags": [],
        "logicLabelInfo": {},
        "siteStatus": 3,
        "latitude": 31.229624,
        "isEticket": false,
        "recReasonType": 2,
        "videos": [],
        "cityId": "872",
        "type": "0",
        "categoryName": "舞蹈芭蕾",
        "priceLow": "280",
        "cityName": "上海",
        "subTitle": "二十周年特别演出",
        "venueId": 56,
        "subHead": "人生的一半寄托。红色的诠释，舞至灵魂深处，每一个肢体语言律动都在解析情感另一半的价值",
        "id": 179735,
        "isSelectSeat": true,
        "longitude": 121.471805,
        "venueCity": "上海",
        "nearestPerformTime": 1576755000000,
        "isNewItem": 0,
        "followStatus": 0,
        "showTag": "",
        "showTime": "2019.12.19-12.20",
        "isSnapUp": false,
        "showStatus": {
          "id": 0,
          "desc": "去购票"
        },
        "logicAddress": "上海",
        "ipvuv": 17629,
        "isAtmospheric": false,
        "isLocal": 0,
        "venueName": "上海大剧院-大剧场",
        "priceStr": "280-580",
        "upTime": 1570777325000,
        "isGeneralAgent": false,
        "tourProjects": [],
        "name": "金星舞蹈团成立二十周年特别演出",
        "verticalPic": "https://pimg.dmcdn.cn/perform/project/1797/179735_n.jpg?_t=1574658041344",
        "formattedPriceStr": "280-580"
      },
      {
        "promotionTags": [],
        "logicLabelInfo": {},
        "siteStatus": 3,
        "latitude": 31.21371,
        "isEticket": false,
        "recReasonType": 2,
        "videos": [],
        "cityId": "872",
        "type": "1",
        "categoryName": "舞蹈芭蕾",
        "priceLow": "80",
        "cityName": "上海",
        "subTitle": "",
        "venueId": 1821007,
        "subHead": "",
        "id": 606959306524,
        "isSelectSeat": true,
        "longitude": 121.45471,
        "venueCity": "上海",
        "nearestPerformTime": 1578137400000,
        "isNewItem": 1,
        "followStatus": 0,
        "showTag": "",
        "showTime": "2020.01.04 周六 19:30",
        "isSnapUp": false,
        "showStatus": {
          "id": 0,
          "desc": "去购票"
        },
        "logicAddress": "上海",
        "ipvuv": 3366,
        "isAtmospheric": false,
        "isLocal": 0,
        "venueName": "上音歌剧院",
        "priceStr": "80-680",
        "upTime": 1572328428000,
        "isGeneralAgent": false,
        "tourProjects": [],
        "name": "俄罗斯国家芭蕾舞剧院——阿斯特拉罕芭蕾舞团2020新版芭蕾舞剧《天鹅湖》",
        "verticalPic": "https://img.alicdn.com/bao/uploaded/https://img.alicdn.com/imgextra/i2/2251059038/O1CN01XsNKAE2GdSCvOz7sV_!!2251059038.png",
        "formattedPriceStr": "80-680"
      },
      {
        "promotionTags": [
          "套票"
        ],
        "logicLabelInfo": {},
        "siteStatus": 3,
        "latitude": 31.222792,
        "isEticket": false,
        "recReasonType": 2,
        "videos": [],
        "cityId": "872",
        "type": "0",
        "categoryName": "舞蹈芭蕾",
        "priceLow": "80",
        "cityName": "上海",
        "subTitle": "经典弗拉门戈舞剧",
        "venueId": 56852,
        "subHead": "世界三大弗拉门戈舞团之一",
        "id": 179917,
        "isSelectSeat": true,
        "longitude": 121.541252,
        "venueCity": "上海",
        "nearestPerformTime": 1579346100000,
        "isNewItem": 0,
        "followStatus": 0,
        "showTag": "",
        "showTime": "2020-1-18 19:15",
        "isSnapUp": false,
        "showStatus": {
          "id": 0,
          "desc": "去购票"
        },
        "logicAddress": "东方艺术中心-歌剧厅",
        "ipvuv": 4777,
        "isAtmospheric": false,
        "isLocal": 0,
        "venueName": "东方艺术中心-歌剧厅",
        "priceStr": "80-1280",
        "upTime": 1571811897000,
        "isGeneralAgent": false,
        "tourProjects": [],
        "name": "西班牙格拉纳达弗拉门戈舞团经典弗拉门戈舞剧《卡门》白金版",
        "verticalPic": "https://pimg.dmcdn.cn/perform/project/1799/179917_n.jpg?_t=1571811995664",
        "formattedPriceStr": "80-1280"
      }
    ],
    "total": 32,
    "discountInfo": "",
    "_prism_lk": {
      "_qid": "b2c25a94-1a62-11ea-be3c-313ac8d559ef",
      "_skey": "b2c25a93-1a62-11ea-be3c-b5690e5f4880"
    }
  },
  "ret": [
    "SUCCESS::调用成功"
  ],
  "v": "1.0"
}